setup.py
hklabk2/__init__.py
hklabk2/cFunction.py
hklabk2.egg-info/PKG-INFO
hklabk2.egg-info/SOURCES.txt
hklabk2.egg-info/dependency_links.txt
hklabk2.egg-info/requires.txt
hklabk2.egg-info/top_level.txt