Metadata-Version: 2.1
Name: hklabk2
Version: 0.0.12
Summary: isoweek calculation and so on
Home-page: UNKNOWN
Author: kkm
Author-email: kimkyongmin2@daum.net
License: MIT
Keywords: calendar,isoweek,listsum
Platform: UNKNOWN
